oonidata/__about__.py
oonidata/__init__.py
oonidata/apiclient.py
oonidata/compat.py
oonidata/dataclient.py
oonidata/datautils.py
oonidata/main.py
oonidata/cli/__init__.py
oonidata/cli/command.py
oonidata/legacy/normalize_yamlooni.py
oonidata/models/__init__.py
oonidata/models/analysis.py
oonidata/models/base.py
oonidata/models/dataformats.py
oonidata/models/experiment_result.py
oonidata/models/observations.py
oonidata/models/nettests/__init__.py
oonidata/models/nettests/base_measurement.py
oonidata/models/nettests/browser_web.py
oonidata/models/nettests/dnscheck.py
oonidata/models/nettests/facebook_messenger.py
oonidata/models/nettests/http_header_field_manipulation.py
oonidata/models/nettests/http_invalid_request_line.py
oonidata/models/nettests/signal.py
oonidata/models/nettests/stun_reachability.py
oonidata/models/nettests/telegram.py
oonidata/models/nettests/tor.py
oonidata/models/nettests/urlgetter.py
oonidata/models/nettests/web_connectivity.py
oonidata/models/nettests/whatsapp.py
oonidata-0.3.0.dist-info/METADATA
oonidata-0.3.0.dist-info/WHEEL
oonidata-0.3.0.dist-info/RECORD
