Metadata-Version: 2.3
Name: oonidata
Version: 0.3.0
Author-email: OONI <contact@ooni.org>
Requires-Dist: boto3~=1.24
Requires-Dist: click-loglevel~=0.5.0
Requires-Dist: click~=8.0.0
Requires-Dist: cryptography~=38.0.3
Requires-Dist: lxml~=4.9
Requires-Dist: lz4~=4.0
Requires-Dist: mashumaro~=3.0
Requires-Dist: orjson~=3.8
Requires-Dist: pyopenssl~=22.1
Requires-Dist: pyyaml~=6.0
Requires-Dist: requests~=2.27
Requires-Dist: tabulate~=0.9.0
Requires-Dist: tqdm~=4.64
